ESG_Engine/__init__.py
ESG_Engine/client/__init__.py
ESG_Engine/client/animation.py
ESG_Engine/client/camera.py
ESG_Engine/client/client_core.py
ESG_Engine/client/client_network.py
ESG_Engine/client/event_handler.py
ESG_Engine/client/particles_emitter.py
ESG_Engine/client/particles_emitters_manager.py
ESG_Engine/client/player.py
ESG_Engine/client/renderer.py
ESG_Engine/client/sound_manager.py
ESG_Engine/core/__init__.py
ESG_Engine/core/clock.py
ESG_Engine/core/constants.py
ESG_Engine/core/engine_core.py
ESG_Engine/core/entity.py
ESG_Engine/core/entity_manager.py
ESG_Engine/core/map.py
ESG_Engine/core/network.py
ESG_Engine/core/network_event.py
ESG_Engine/core/packet.py
ESG_Engine/core/received_packet.py
ESG_Engine/core/server_client.py
ESG_Engine/server/__init__.py
ESG_Engine/server/server_core.py
ESG_Engine/server/server_network.py
ESG_Engine-0.1.7.dist-info/LICENSE.txt
ESG_Engine-0.1.7.dist-info/METADATA
ESG_Engine-0.1.7.dist-info/WHEEL
ESG_Engine-0.1.7.dist-info/top_level.txt
ESG_Engine-0.1.7.dist-info/RECORD
