Metadata-Version: 2.1
Name: ESG-Engine
Version: 0.1.7
Summary: A little online game engine.
Home-page: https://github.com/yannis300307/ES_Engine
Download-URL: 
Author: Yannis300307
License: MIT
Keywords: python,Game Engine,Pygame
License-File: LICENSE.txt
Requires-Dist: pygame
